{
	"pages": [ //pages数组中第一项表示应用启动页，参考：https://uniapp.dcloud.io/collocation/pages
		{
			"path": "pages/index/index"
		},
		{
			"path": "pages/index/faxian"
		},
		{
			"path": "pages/index/xiaoxi"
		},
		{
			"path": "pages/index/my"
		},
		{
			"path": "pages/index/login_xuanze"
		},
		{
			"path": "pages/qy/index",
			"style": {
			"enablePullDownRefresh": true  //允许上拉加载和下拉刷新为true
			}
		},
		{
			"path": "pages/qy/xiaoxi"
		},
		{
			"path": "pages/qy/my"
		},
		{
			"path": "pages/qy/fabu_zhiwei"
		},
		{
			"path": "pages/qy/fabu_success"
		},
		
		{
			"path": "pages/qy/zhiwei_guanli"
		},
		{
			"path": "pages/qy/zhuye"
		},
		{
			"path": "pages/qy/mian_jilu"
		},
		{
			"path": "pages/qy/geren"
		},
		{
			"path": "pages/qy/zhiding"
		},
		{
			"path": "pages/qy/jiben_xinxi"
		},
		{
			"path": "pages/qy/wanshan_xinxi"
		},
		{
			"path": "pages/qy/huan_shenfen"
		},
		{
			"path": "pages/qy/shaixuan"
		},
		{
			"path": "pages/qy/my_gongsi"
		},
		{
			"path": "pages/qy/mian_xq"
		},
		{
			"path": "pages/qy/mian_richeng"
		},
		{
			"path": "pages/qy/shoucang"
		},
		{
			"path": "pages/qy/mian_yaoqing"
		},
		{
			"path": "pages/qy/gongsi_xq"
		},
		{
			"path": "pages/qy/jianli_xq"
		},
		{
			"path": "pages/qy/chat"
		},
		{
			"path": "pages/qy/search"
		}
	],

	"globalStyle": {
		"titleNView":false,
		"navigationBarTextStyle": "black"
	},
	"tabBar": {
			"color":"#8a8a8a",
			"selectedColor":"#00c6c9",
			"borderStyle":"black",
			"backgroundColor":"#ffffff",
			"list": [
				{
					"pagePath":"pages/index/index",
					"text":"职位",
					"iconPath":"static/index_img/tabber1.png",
					"selectedIconPath":"static/index_img/tabber1_on.png"
				},
				{
					"pagePath":"pages/index/faxian",
					"text":"发现",
					"iconPath":"static/index_img/tabber2.png",
					"selectedIconPath":"static/index_img/tabber2_on.png"
				},
				{
					"pagePath":"pages/index/xiaoxi",
					"text":"消息",
					"iconPath":"static/index_img/tabber3.png",
					"selectedIconPath":"static/index_img/tabber3_on.png"
				},
				{
					"pagePath":"pages/index/my",
					"text":"我的",
					"iconPath":"static/index_img/tabber4.png",
					"selectedIconPath":"static/index_img/tabber4_on.png"
				}
			
			]	
		 }
}
